e80_sdk/__init__.py
e80_sdk/eighty80.py
e80_sdk/endpoint.py
e80_sdk/errors.py
e80_sdk/fastapi.py
e80_sdk/generate.py
e80_sdk/py.typed
e80_sdk/sandbox.py
e80_sdk/secrets.py
e80_sdk/internal/__init__.py
e80_sdk/internal/environment.py
e80_sdk/internal/httpx_async.py
e80_sdk/internal/platform.py
e80_sdk-0.1.0a8.dist-info/METADATA
e80_sdk-0.1.0a8.dist-info/WHEEL
e80_sdk-0.1.0a8.dist-info/RECORD
